credis/__init__.py
credis/base.pyx
credis/geventpool.pyx
credis/base.c
credis/base.cpython-310-darwin.so
credis/geventpool.c
credis/geventpool.cpython-310-darwin.so
credis-2.0.2.dist-info/LICENSE
credis-2.0.2.dist-info/METADATA
credis-2.0.2.dist-info/WHEEL
credis-2.0.2.dist-info/RECORD
