Metadata-Version: 2.1
Name: credis
Version: 2.0.2
Summary: high performance redis client implemented with cython
Home-page: https://github.com/yihuang/credis
License: MIT
Author: yihuang
Author-email: yi.codeplayer@gmail.com
Requires-Python: >=3.7,<4.0
Classifier: Development Status :: 6 - Mature
Classifier: Intended Audience :: Developers
Classifier: License :: OSI Approved :: MIT License
Classifier: Programming Language :: Cython
Classifier: Programming Language :: Python
Classifier: Programming Language :: Python :: 3
Classifier: Programming Language :: Python :: 3.7
Classifier: Programming Language :: Python :: 3.8
Classifier: Programming Language :: Python :: 3.9
Classifier: Programming Language :: Python :: 3.10
Classifier: Programming Language :: Python :: 3.11
Classifier: Topic :: Database
Requires-Dist: hiredis (>=2.2.3,<3.0.0)
Project-URL: Repository, https://github.com/yihuang/credis
